streamlit_tesseract_scanner/__init__.py
streamlit_tesseract_scanner/frontend/index.html
streamlit_tesseract_scanner/frontend/main.js
streamlit_tesseract_scanner/frontend/streamlit-component-lib.js
streamlit_tesseract_scanner-0.1.0.dist-info/LICENSE
streamlit_tesseract_scanner-0.1.0.dist-info/METADATA
streamlit_tesseract_scanner-0.1.0.dist-info/WHEEL
streamlit_tesseract_scanner-0.1.0.dist-info/top_level.txt
streamlit_tesseract_scanner-0.1.0.dist-info/RECORD
