Metadata-Version: 2.1
Name: streamlit-tesseract-scanner
Version: 0.1.0
Summary: OCR Scanner use tesseract
Home-page: https://github.com/phamxtien/streamlit_tesseract_scanner
Author: Pham Xuan Tien
Author-email: phamxtien@gmail.com
License: UNKNOWN
Platform: UNKNOWN
Requires-Python: >=3.9
License-File: LICENSE
Requires-Dist: streamlit (>=1.15)
